{"type":"FeatureCollection", "features": [
{"type":"Feature","geometry":{"type":"Point","coordinates":[-118.18576373755369,34.495589118796566]},"properties":{"population":7185,"geoid":"16000US0600212","name":"Acton, CA"}},
{"type":"Feature","geometry":{"type":"Point","coordinates":[-118.7608816740237,34.15100288907385]},"properties":{"population":20636,"geoid":"16000US0600394","name":"Agoura Hills, CA"}},
{"type":"Feature","geometry":{"type":"Point","coordinates":[-118.31599570933383,34.50442354241343]},"properties":{"population":3728,"geoid":"16000US0600450","name":"Agua Dulce, CA"}},
{"type":"Feature","geometry":{"type":"Point","coordinates":[-118.13551415247267,34.083973460339635]},"properties":{"population":84974,"geoid":"16000US0600884","name":"Alhambra, CA"}},
{"type":"Feature","geometry":{"type":"Point","coordinates":[-118.33496427151162,33.88842811309204]},"properties":{"population":8097,"geoid":"16000US0601150","name":"Alondra Park, CA"}},
{"type":"Feature","geometry":{"type":"Point","coordinates":[-118.13448344615979,34.19272899047893]},"properties":{"population":45146,"geoid":"16000US0601290","name":"Altadena, CA"}},
{"type":"Feature","geometry":{"type":"Point","coordinates":[-118.03730737675767,34.13419254117314]},"properties":{"population":58207,"geoid":"16000US0602462","name":"Arcadia, CA"}},
{"type":"Feature","geometry":{"type":"Point","coordinates":[-118.0806355258351,33.86759291046479]},"properties":{"population":16817,"geoid":"16000US0602896","name":"Artesia, CA"}},
{"type":"Feature","geometry":{"type":"Point","coordinates":[-118.00260770076515,34.03808136337736]},"properties":{"population":15903,"geoid":"16000US0603344","name":"Avocado Heights, CA"}},
{"type":"Feature","geometry":{"type":"Point","coordinates":[-117.91203690234354,34.138675155928496]},"properties":{"population":49544,"geoid":"16000US0603386","name":"Azusa, CA"}},
{"type":"Feature","geometry":{"type":"Point","coordinates":[-117.97210092020565,34.082871516151755]},"properties":{"population":76222,"geoid":"16000US0603666","name":"Baldwin Park, CA"}},
{"type":"Feature","geometry":{"type":"Point","coordinates":[-118.17973442873983,33.98007684088629]},"properties":{"population":35809,"geoid":"16000US0604870","name":"Bell, CA"}},
{"type":"Feature","geometry":{"type":"Point","coordinates":[-118.12710375640522,33.888039413706046]},"properties":{"population":77529,"geoid":"16000US0604982","name":"Bellflower, CA"}},
{"type":"Feature","geometry":{"type":"Point","coordinates":[-118.1550130362935,33.96633171531758]},"properties":{"population":42641,"geoid":"16000US0604996","name":"Bell Gardens, CA"}},
{"type":"Feature","geometry":{"type":"Point","coordinates":[-118.40211365224471,34.07855858763281]},"properties":{"population":34362,"geoid":"16000US0606308","name":"Beverly Hills, CA"}},
{"type":"Feature","geometry":{"type":"Point","coordinates":[-117.96835695595651,34.15354530105806]},"properties":{"population":916,"geoid":"16000US0607946","name":"Bradbury, CA"}},
{"type":"Feature","geometry":{"type":"Point","coordinates":[-118.32349034377091,34.18790505054682]},"properties":{"population":104275,"geoid":"16000US0608954","name":"Burbank, CA"}},
{"type":"Feature","geometry":{"type":"Point","coordinates":[-118.66883467684373,34.13746409675196]},"properties":{"population":24077,"geoid":"16000US0609598","name":"Calabasas, CA"}},
{"type":"Feature","geometry":{"type":"Point","coordinates":[-118.2559313303459,33.83740779588253]},"properties":{"population":92517,"geoid":"16000US0611530","name":"Carson, CA"}},
{"type":"Feature","geometry":{"type":"Point","coordinates":[-118.63164629829326,34.48178019109333]},"properties":{"population":18921,"geoid":"16000US0611796","name":"Castaic, CA"}},
{"type":"Feature","geometry":{"type":"Point","coordinates":[-118.06861541056061,33.86773783858504]},"properties":{"population":50172,"geoid":"16000US0612552","name":"Cerritos, CA"}},
{"type":"Feature","geometry":{"type":"Point","coordinates":[-117.85631491278953,34.10248236683555]},"properties":{"population":9760,"geoid":"16000US0612734","name":"Charter Oak, CA"}},
{"type":"Feature","geometry":{"type":"Point","coordinates":[-117.88895362119091,34.11608525343802]},"properties":{"population":10771,"geoid":"16000US0613560","name":"Citrus, CA"}},
{"type":"Feature","geometry":{"type":"Point","coordinates":[-117.71552930778144,34.12595234064816]},"properties":{"population":36025,"geoid":"16000US0613756","name":"Claremont, CA"}},
{"type":"Feature","geometry":{"type":"Point","coordinates":[-118.15190229044592,33.996303303532265]},"properties":{"population":12933,"geoid":"16000US0614974","name":"Commerce, CA"}},
{"type":"Feature","geometry":{"type":"Point","coordinates":[-118.22563342524344,33.89316052062303]},"properties":{"population":97301,"geoid":"16000US0615044","name":"Compton, CA"}},
{"type":"Feature","geometry":{"type":"Point","coordinates":[-117.88199541184753,34.090265291368446]},"properties":{"population":48403,"geoid":"16000US0616742","name":"Covina, CA"}},
{"type":"Feature","geometry":{"type":"Point","coordinates":[-118.1830861083128,33.96311590046998]},"properties":{"population":24016,"geoid":"16000US0617498","name":"Cudahy, CA"}},
{"type":"Feature","geometry":{"type":"Point","coordinates":[-118.39682882674222,34.00578429411322]},"properties":{"population":39295,"geoid":"16000US0617568","name":"Culver City, CA"}},
{"type":"Feature","geometry":{"type":"Point","coordinates":[-118.36929219623877,33.91671278377056]},"properties":{"population":10065,"geoid":"16000US0618352","name":"Del Aire, CA"}},
{"type":"Feature","geometry":{"type":"Point","coordinates":[-118.15353685016545,34.590259122875416]},"properties":{"population":2496,"geoid":"16000US0619052","name":"Desert View Highlands, CA"}},
{"type":"Feature","geometry":{"type":"Point","coordinates":[-117.8161026431712,33.99916046362253]},"properties":{"population":56434,"geoid":"16000US0619192","name":"Diamond Bar, CA"}},
{"type":"Feature","geometry":{"type":"Point","coordinates":[-118.1311501152043,33.93786725103775]},"properties":{"population":112901,"geoid":"16000US0619766","name":"Downey, CA"}},
{"type":"Feature","geometry":{"type":"Point","coordinates":[-117.95044456493783,34.16096929604582]},"properties":{"population":21713,"geoid":"16000US0619990","name":"Duarte, CA"}},
{"type":"Feature","geometry":{"type":"Point","coordinates":[-118.16914274555694,34.032627938521614]},"properties":{"population":119827,"geoid":"16000US0620802","name":"East Los Angeles, CA"}},
{"type":"Feature","geometry":{"type":"Point","coordinates":[-118.07754061292368,34.13775928233198]},"properties":{"population":5971,"geoid":"16000US0620984","name":"East Pasadena, CA"}},
{"type":"Feature","geometry":{"type":"Point","coordinates":[-118.19462817305559,33.89756960129339]},"properties":{"population":16734,"geoid":"16000US0621034","name":"East Rancho Dominguez, CA"}},
{"type":"Feature","geometry":{"type":"Point","coordinates":[-118.08067567601228,34.11983682753396]},"properties":{"population":15932,"geoid":"16000US0621096","name":"East San Gabriel, CA"}},
{"type":"Feature","geometry":{"type":"Point","coordinates":[-117.98872637274683,33.92437325799055]},"properties":{"population":10391,"geoid":"16000US0621292","name":"East Whittier, CA"}},
{"type":"Feature","geometry":{"type":"Point","coordinates":[-118.37839312639029,34.6589923708096]},"properties":{"population":1895,"geoid":"16000US0621964","name":"Elizabeth Lake, CA"}},
{"type":"Feature","geometry":{"type":"Point","coordinates":[-118.02907196543043,34.0739196572419]},"properties":{"population":115669,"geoid":"16000US0622230","name":"El Monte, CA"}},
{"type":"Feature","geometry":{"type":"Point","coordinates":[-118.24466746521928,33.96816065272421]},"properties":{"population":64162,"geoid":"16000US0624477","name":"Florence-Graham, CA"}},
{"type":"Feature","geometry":{"type":"Point","coordinates":[-118.30723979105029,33.894338076382226]},"properties":{"population":59924,"geoid":"16000US0628168","name":"Gardena, CA"}},
{"type":"Feature","geometry":{"type":"Point","coordinates":[-118.24680785760205,34.18188813651579]},"properties":{"population":200372,"geoid":"16000US0630000","name":"Glendale, CA"}},
{"type":"Feature","geometry":{"type":"Point","coordinates":[-117.84692806567465,34.144939255793794]},"properties":{"population":51773,"geoid":"16000US0630014","name":"Glendora, CA"}},
{"type":"Feature","geometry":{"type":"Point","coordinates":[-118.40589644296551,34.6172217410221]},"properties":{"population":973,"geoid":"16000US0631092","name":"Green Valley, CA"}},
{"type":"Feature","geometry":{"type":"Point","coordinates":[-117.97283147720968,33.99696540799129]},"properties":{"population":54970,"geoid":"16000US0631596","name":"Hacienda Heights, CA"}},
{"type":"Feature","geometry":{"type":"Point","coordinates":[-118.66657902839138,34.48177653944743]},"properties":{"population":1085,"geoid":"16000US0632385","name":"Hasley Canyon, CA"}},
{"type":"Feature","geometry":{"type":"Point","coordinates":[-118.07284734927872,33.83033206667373]},"properties":{"population":14411,"geoid":"16000US0632506","name":"Hawaiian Gardens, CA"}},
{"type":"Feature","geometry":{"type":"Point","coordinates":[-118.34767483521131,33.91466777977986]},"properties":{"population":87370,"geoid":"16000US0632548","name":"Hawthorne, CA"}},
{"type":"Feature","geometry":{"type":"Point","coordinates":[-118.39629728268008,33.86527501067743]},"properties":{"population":19650,"geoid":"16000US0633364","name":"Hermosa Beach, CA"}},
{"type":"Feature","geometry":{"type":"Point","coordinates":[-118.66120390551649,34.16374400059361]},"properties":{"population":1634,"geoid":"16000US0633518","name":"Hidden Hills, CA"}},
{"type":"Feature","geometry":{"type":"Point","coordinates":[-118.21666707319046,33.97998117305616]},"properties":{"population":58694,"geoid":"16000US0636056","name":"Huntington Park, CA"}},
{"type":"Feature","geometry":{"type":"Point","coordinates":[-117.92638309350927,34.01738970810954]},"properties":{"population":344,"geoid":"16000US0636490","name":"Industry, CA"}},
{"type":"Feature","geometry":{"type":"Point","coordinates":[-118.3443008156444,33.95645382385194]},"properties":{"population":110327,"geoid":"16000US0636546","name":"Inglewood, CA"}},
{"type":"Feature","geometry":{"type":"Point","coordinates":[-117.96370243677308,34.11211181795286]},"properties":{"population":1405,"geoid":"16000US0636826","name":"Irwindale, CA"}},
{"type":"Feature","geometry":{"type":"Point","coordinates":[-118.2001657182021,34.20967619960872]},"properties":{"population":20374,"geoid":"16000US0639003","name":"La Cañada Flintridge, CA"}},
{"type":"Feature","geometry":{"type":"Point","coordinates":[-118.23526579839118,34.232160226489455]},"properties":{"population":19500,"geoid":"16000US0639045","name":"La Crescenta-Montrose, CA"}},
{"type":"Feature","geometry":{"type":"Point","coordinates":[-118.37400485811608,33.99718324169779]},"properties":{"population":7090,"geoid":"16000US0639108","name":"Ladera Heights, CA"}},
{"type":"Feature","geometry":{"type":"Point","coordinates":[-117.95098597732716,33.96024531324082]},"properties":{"population":5383,"geoid":"16000US0639304","name":"La Habra Heights, CA"}},
{"type":"Feature","geometry":{"type":"Point","coordinates":[-118.45890474365932,34.683252598982335]},"properties":{"population":587,"geoid":"16000US0639556","name":"Lake Hughes, CA"}},
{"type":"Feature","geometry":{"type":"Point","coordinates":[-117.8339099334078,34.60966608486408]},"properties":{"population":11469,"geoid":"16000US0639612","name":"Lake Los Angeles, CA"}},
{"type":"Feature","geometry":{"type":"Point","coordinates":[-118.1221872088311,33.847061572875695]},"properties":{"population":80771,"geoid":"16000US0639892","name":"Lakewood, CA"}},
{"type":"Feature","geometry":{"type":"Point","coordinates":[-118.00929256289345,33.902507044440355]},"properties":{"population":48974,"geoid":"16000US0640032","name":"La Mirada, CA"}},
{"type":"Feature","geometry":{"type":"Point","coordinates":[-118.1798206442281,34.693559534532945]},"properties":{"population":159662,"geoid":"16000US0640130","name":"Lancaster, CA"}},
{"type":"Feature","geometry":{"type":"Point","coordinates":[-117.95336622360227,34.03230388062549]},"properties":{"population":40268,"geoid":"16000US0640340","name":"La Puente, CA"}},
{"type":"Feature","geometry":{"type":"Point","coordinates":[-117.77027137524219,34.12074138323627]},"properties":{"population":32358,"geoid":"16000US0640830","name":"La Verne, CA"}},
{"type":"Feature","geometry":{"type":"Point","coordinates":[-118.3531376722005,33.88842273034183]},"properties":{"population":33007,"geoid":"16000US0640886","name":"Lawndale, CA"}},
{"type":"Feature","geometry":{"type":"Point","coordinates":[-118.35854221147103,33.93806479971054]},"properties":{"population":21329,"geoid":"16000US0641180","name":"Lennox, CA"}},
{"type":"Feature","geometry":{"type":"Point","coordinates":[-118.29894212111641,34.614716361118596]},"properties":{"population":1581,"geoid":"16000US0641208","name":"Leona Valley, CA"}},
{"type":"Feature","geometry":{"type":"Point","coordinates":[-117.98085952415254,34.523177595158195]},"properties":{"population":1766,"geoid":"16000US0641880","name":"Littlerock, CA"}},
{"type":"Feature","geometry":{"type":"Point","coordinates":[-118.31745084303083,33.79330624055419]},"properties":{"population":20628,"geoid":"16000US0642468","name":"Lomita, CA"}},
{"type":"Feature","geometry":{"type":"Point","coordinates":[-118.16721398106866,33.77795880424479]},"properties":{"population":468883,"geoid":"16000US0643000","name":"Long Beach, CA"}},
{"type":"Feature","geometry":{"type":"Point","coordinates":[-118.41102276011935,34.10480135443213]},"properties":{"population":3959657,"geoid":"16000US0644000","name":"Los Angeles, CA"}},
{"type":"Feature","geometry":{"type":"Point","coordinates":[-118.20164850732878,33.923961719621204]},"properties":{"population":71022,"geoid":"16000US0644574","name":"Lynwood, CA"}},
{"type":"Feature","geometry":{"type":"Point","coordinates":[-118.78396297927657,34.036765779217504]},"properties":{"population":12846,"geoid":"16000US0645246","name":"Malibu, CA"}},
{"type":"Feature","geometry":{"type":"Point","coordinates":[-118.39712870116517,33.889468877522646]},"properties":{"population":35573,"geoid":"16000US0645400","name":"Manhattan Beach, CA"}},
{"type":"Feature","geometry":{"type":"Point","coordinates":[-118.44859793107828,33.97649273943346]},"properties":{"population":9771,"geoid":"16000US0645806","name":"Marina del Rey, CA"}},
{"type":"Feature","geometry":{"type":"Point","coordinates":[-118.00958972895765,34.1159000423567]},"properties":{"population":5822,"geoid":"16000US0646436","name":"Mayflower Village, CA"}},
{"type":"Feature","geometry":{"type":"Point","coordinates":[-118.18766680447031,33.988505037367815]},"properties":{"population":27542,"geoid":"16000US0646492","name":"Maywood, CA"}},
{"type":"Feature","geometry":{"type":"Point","coordinates":[-117.99208330683548,34.16511992450732]},"properties":{"population":37006,"geoid":"16000US0648648","name":"Monrovia, CA"}},
{"type":"Feature","geometry":{"type":"Point","coordinates":[-118.11078551875336,34.01544474456939]},"properties":{"population":63099,"geoid":"16000US0648816","name":"Montebello, CA"}},
{"type":"Feature","geometry":{"type":"Point","coordinates":[-118.13254534443747,34.04971169225993]},"properties":{"population":60792,"geoid":"16000US0648914","name":"Monterey Park, CA"}},
{"type":"Feature","geometry":{"type":"Point","coordinates":[-118.0238382465607,34.10294676980176]},"properties":{"population":4028,"geoid":"16000US0651820","name":"North El Monte, CA"}},
{"type":"Feature","geometry":{"type":"Point","coordinates":[-118.08290739225845,33.90687891617615]},"properties":{"population":105886,"geoid":"16000US0652526","name":"Norwalk, CA"}},
{"type":"Feature","geometry":{"type":"Point","coordinates":[-118.08808196667803,34.59833146847686]},"properties":{"population":156904,"geoid":"16000US0655156","name":"Palmdale, CA"}},
{"type":"Feature","geometry":{"type":"Point","coordinates":[-118.39735715852794,33.78717120725209]},"properties":{"population":13523,"geoid":"16000US0655380","name":"Palos Verdes Estates, CA"}},
{"type":"Feature","geometry":{"type":"Point","coordinates":[-118.16512657001938,33.89761808413302]},"properties":{"population":54776,"geoid":"16000US0655618","name":"Paramount, CA"}},
{"type":"Feature","geometry":{"type":"Point","coordinates":[-118.13890648568497,34.15971553712924]},"properties":{"population":141246,"geoid":"16000US0656000","name":"Pasadena, CA"}},
{"type":"Feature","geometry":{"type":"Point","coordinates":[-118.08873794185621,33.990172675477794]},"properties":{"population":63432,"geoid":"16000US0656924","name":"Pico Rivera, CA"}},
{"type":"Feature","geometry":{"type":"Point","coordinates":[-117.7625602629129,34.05849030616433]},"properties":{"population":152494,"geoid":"16000US0658072","name":"Pomona, CA"}},
{"type":"Feature","geometry":{"type":"Point","coordinates":[-118.21632590115757,34.652684035277446]},"properties":{"population":10164,"geoid":"16000US0659052","name":"Quartz Hill, CA"}},
{"type":"Feature","geometry":{"type":"Point","coordinates":[-118.36356463638977,33.755389782258845]},"properties":{"population":42271,"geoid":"16000US0659514","name":"Rancho Palos Verdes, CA"}},
{"type":"Feature","geometry":{"type":"Point","coordinates":[-118.37661901757554,33.85747913535825]},"properties":{"population":67700,"geoid":"16000US0660018","name":"Redondo Beach, CA"}},
{"type":"Feature","geometry":{"type":"Point","coordinates":[-118.34716380425111,33.76001562760139]},"properties":{"population":1630,"geoid":"16000US0662602","name":"Rolling Hills, CA"}},
{"type":"Feature","geometry":{"type":"Point","coordinates":[-118.35091518316611,33.778346306598586]},"properties":{"population":8187,"geoid":"16000US0662644","name":"Rolling Hills Estates, CA"}},
{"type":"Feature","geometry":{"type":"Point","coordinates":[-118.04193844071108,34.009108683843294]},"properties":{"population":2612,"geoid":"16000US0662860","name":"Rose Hills, CA"}},
{"type":"Feature","geometry":{"type":"Point","coordinates":[-118.08231473783131,34.06884322808714]},"properties":{"population":54417,"geoid":"16000US0662896","name":"Rosemead, CA"}},
{"type":"Feature","geometry":{"type":"Point","coordinates":[-117.89118962733356,33.97159002858576]},"properties":{"population":50602,"geoid":"16000US0663218","name":"Rowland Heights, CA"}},
{"type":"Feature","geometry":{"type":"Point","coordinates":[-117.809605108967,34.107709777467626]},"properties":{"population":34239,"geoid":"16000US0666070","name":"San Dimas, CA"}},
{"type":"Feature","geometry":{"type":"Point","coordinates":[-118.43624071375079,34.28865208714459]},"properties":{"population":24585,"geoid":"16000US0666140","name":"San Fernando, CA"}},
{"type":"Feature","geometry":{"type":"Point","coordinates":[-118.09872730890581,34.09499472311268]},"properties":{"population":40242,"geoid":"16000US0667042","name":"San Gabriel, CA"}},
{"type":"Feature","geometry":{"type":"Point","coordinates":[-118.11318312162392,34.12237838151804]},"properties":{"population":13285,"geoid":"16000US0668224","name":"San Marino, CA"}},
{"type":"Feature","geometry":{"type":"Point","coordinates":[-118.10251698379446,34.13921834939387]},"properties":{"population":1932,"geoid":"16000US0668308","name":"San Pasqual, CA"}},
{"type":"Feature","geometry":{"type":"Point","coordinates":[-118.49916975059423,34.41558005261109]},"properties":{"population":209478,"geoid":"16000US0669088","name":"Santa Clarita, CA"}},
{"type":"Feature","geometry":{"type":"Point","coordinates":[-118.06253642579286,33.933046871483604]},"properties":{"population":17791,"geoid":"16000US0669154","name":"Santa Fe Springs, CA"}},
{"type":"Feature","geometry":{"type":"Point","coordinates":[-118.05033851247316,34.16872028953178]},"properties":{"population":11006,"geoid":"16000US0671806","name":"Sierra Madre, CA"}},
{"type":"Feature","geometry":{"type":"Point","coordinates":[-118.16818172843149,33.80295150080674]},"properties":{"population":11538,"geoid":"16000US0671876","name":"Signal Hill, CA"}},
{"type":"Feature","geometry":{"type":"Point","coordinates":[-118.04832422040272,34.04934266953625]},"properties":{"population":20727,"geoid":"16000US0672996","name":"South El Monte, CA"}},
{"type":"Feature","geometry":{"type":"Point","coordinates":[-118.19255054040204,33.944732256770976]},"properties":{"population":95103,"geoid":"16000US0673080","name":"South Gate, CA"}},
{"type":"Feature","geometry":{"type":"Point","coordinates":[-117.99585646814359,34.12342673909533]},"properties":{"population":7192,"geoid":"16000US0673167","name":"South Monrovia Island, CA"}},
{"type":"Feature","geometry":{"type":"Point","coordinates":[-118.15730664116154,34.11026520428117]},"properties":{"population":25824,"geoid":"16000US0673220","name":"South Pasadena, CA"}},
{"type":"Feature","geometry":{"type":"Point","coordinates":[-118.09616026104356,34.048892987324734]},"properties":{"population":8643,"geoid":"16000US0673276","name":"South San Gabriel, CA"}},
{"type":"Feature","geometry":{"type":"Point","coordinates":[-117.90422332840292,34.012281534332544]},"properties":{"population":20593,"geoid":"16000US0673290","name":"South San Jose Hills, CA"}},
{"type":"Feature","geometry":{"type":"Point","coordinates":[-118.03114719399373,33.93360112221195]},"properties":{"population":60096,"geoid":"16000US0673430","name":"South Whittier, CA"}},
{"type":"Feature","geometry":{"type":"Point","coordinates":[-118.58850976253473,34.389386100545195]},"properties":{"population":19364,"geoid":"16000US0674130","name":"Stevenson Ranch, CA"}},
{"type":"Feature","geometry":{"type":"Point","coordinates":[-117.95585615067463,34.559617734656584]},"properties":{"population":13516,"geoid":"16000US0677308","name":"Sun Village, CA"}},
{"type":"Feature","geometry":{"type":"Point","coordinates":[-118.05794946348395,34.102158822763215]},"properties":{"population":36137,"geoid":"16000US0678148","name":"Temple City, CA"}},
{"type":"Feature","geometry":{"type":"Point","coordinates":[-118.60527751376698,34.096428603896015]},"properties":{"population":7449,"geoid":"16000US0678960","name":"Topanga, CA"}},
{"type":"Feature","geometry":{"type":"Point","coordinates":[-118.34162535334406,33.83460508667466]},"properties":{"population":146392,"geoid":"16000US0680000","name":"Torrance, CA"}},
{"type":"Feature","geometry":{"type":"Point","coordinates":[-117.93005283619011,34.040036164884896]},"properties":{"population":25296,"geoid":"16000US0681638","name":"Valinda, CA"}},
{"type":"Feature","geometry":{"type":"Point","coordinates":[-118.67178442011965,34.450422896166764]},"properties":{"population":2996,"geoid":"16000US0681967","name":"Val Verde, CA"}},
{"type":"Feature","geometry":{"type":"Point","coordinates":[-118.2105381464349,34.0019308699796]},"properties":{"population":90,"geoid":"16000US0682422","name":"Vernon, CA"}},
{"type":"Feature","geometry":{"type":"Point","coordinates":[-118.34835038199108,33.99550863703472]},"properties":{"population":11580,"geoid":"16000US0682667","name":"View Park-Windsor Hills, CA"}},
{"type":"Feature","geometry":{"type":"Point","coordinates":[-117.92381425497915,34.098229906551694]},"properties":{"population":17008,"geoid":"16000US0682815","name":"Vincent, CA"}},
{"type":"Feature","geometry":{"type":"Point","coordinates":[-117.85930985028638,34.03343452000098]},"properties":{"population":30008,"geoid":"16000US0683332","name":"Walnut, CA"}},
{"type":"Feature","geometry":{"type":"Point","coordinates":[-118.22197147138169,33.96823234858066]},"properties":{"population":16034,"geoid":"16000US0683402","name":"Walnut Park, CA"}},
{"type":"Feature","geometry":{"type":"Point","coordinates":[-118.3032971422806,33.92345527134749]},"properties":{"population":8574,"geoid":"16000US0684116","name":"West Athens, CA"}},
{"type":"Feature","geometry":{"type":"Point","coordinates":[-118.29312691376738,33.82293513253259]},"properties":{"population":22537,"geoid":"16000US0684144","name":"West Carson, CA"}},
{"type":"Feature","geometry":{"type":"Point","coordinates":[-117.91126016294808,34.05544352624421]},"properties":{"population":107242,"geoid":"16000US0684200","name":"West Covina, CA"}},
{"type":"Feature","geometry":{"type":"Point","coordinates":[-118.37183110414894,34.08826711526223]},"properties":{"population":36384,"geoid":"16000US0684410","name":"West Hollywood, CA"}},
{"type":"Feature","geometry":{"type":"Point","coordinates":[-118.82204566018822,34.13690113750696]},"properties":{"population":8424,"geoid":"16000US0684438","name":"Westlake Village, CA"}},
{"type":"Feature","geometry":{"type":"Point","coordinates":[-118.30183706839796,33.94167917489193]},"properties":{"population":33723,"geoid":"16000US0684592","name":"Westmont, CA"}},
{"type":"Feature","geometry":{"type":"Point","coordinates":[-117.96802587566415,34.05117612142611]},"properties":{"population":23629,"geoid":"16000US0684774","name":"West Puente Valley, CA"}},
{"type":"Feature","geometry":{"type":"Point","coordinates":[-118.26878007249174,33.90571605281681]},"properties":{"population":22932,"geoid":"16000US0684780","name":"West Rancho Dominguez, CA"}},
{"type":"Feature","geometry":{"type":"Point","coordinates":[-118.06892492448051,33.976001505500115]},"properties":{"population":27144,"geoid":"16000US0684921","name":"West Whittier-Los Nietos, CA"}},
{"type":"Feature","geometry":{"type":"Point","coordinates":[-118.01865960981223,33.96762481656488]},"properties":{"population":86523,"geoid":"16000US0685292","name":"Whittier, CA"}},
{"type":"Feature","geometry":{"type":"Point","coordinates":[-118.23616232995087,33.919853210152354]},"properties":{"population":22402,"geoid":"16000US0685614","name":"Willowbrook, CA"}}
]}